__init__.py
copy.py
download.py
dump.py
files.py
attributes/__init__.py
attributes/aoty.py
attributes/local_dirs.py
attributes/prog.py
classes/Album.py
classes/DuplicatesList.py
classes/MusicList.py
classes/__init__.py
debug/__init__.py
debug/logging.py
debug/test_data.py
decorators/__init__.py
decorators/choice.py
decorators/commands.py
decorators/data.py
decorators/decorators.py
decorators/groups.py
decorators/number.py
defaults/__init__.py
defaults/choice.py
defaults/click.py
defaults/defaults.py
defaults/download.py
defaults/path.py
get/__init__.py
get/data.py
get/file.py
scripts/__init__.py
scripts/musiclists.py
musiclists-0.2.2.dist-info/LICENSE
musiclists-0.2.2.dist-info/METADATA
musiclists-0.2.2.dist-info/WHEEL
musiclists-0.2.2.dist-info/entry_points.txt
musiclists-0.2.2.dist-info/top_level.txt
musiclists-0.2.2.dist-info/RECORD
