Metadata-Version: 2.1
Name: musiclists
Version: 0.2.2
Summary: Download, filter and transform data from music review aggregator websites.
Author-email: Mauricio Valentín Barón Salinas <baronsmv@gmail.com>
License:                     GNU GENERAL PUBLIC LICENSE
Project-URL: Homepage, https://github.com/baronsmv/musiclists
Project-URL: Issues, https://github.com/baronsmv/musiclists/issues
Requires-Python: >=3.8
License-File: LICENSE
Requires-Dist: bs4
Requires-Dist: click
Requires-Dist: click_help_colors
Requires-Dist: m3u8
Requires-Dist: mutagen
Requires-Dist: polars
